{
  "1": {
    "Communication & Scheduling": 185831,
    "Business": 146969,
    "Uncategorized": 36769,
    "Design & Composition": 16461,
    "News & Opinion": 7281,
    "Reference & Learning": 13027,
    "Shopping": 3468,
    "Utilities": 4559,
    "Social Networking": 7976,
    "Entertainment": 16862,
    "Software Development": 712,
    "Other Work": 23064
  },
  "2": {
    "Uncategorized": 11181,
    "Utilities": 1642,
    "Business": 47536,
    "Other Work": 13168,
    "Communication & Scheduling": 64990,
    "Social Networking": 8757,
    "Design & Composition": 7515,
    "News & Opinion": 4023,
    "Reference & Learning": 3971,
    "Entertainment": 19644,
    "Software Development": 467,
    "Shopping": 497
  },
  "3": {},
  "4": {},
  "5": {},
  "6": {},
  "7": {},
  "8": {},
  "9": {},
  "10": {},
  "11": {},
  "12": {}
}