{
  "2020-10-18": {
    "Business": 11036,
    "Communication & Scheduling": 5882,
    "Reference & Learning": 4167,
    "Design & Composition": 3945,
    "Uncategorized": 2878,
    "Shopping": 2833,
    "Entertainment": 979,
    "News & Opinion": 717,
    "Social Networking": 637,
    "Utilities": 520,
    "Software Development": 53
  },
  "2020-10-19": {
    "Communication & Scheduling": 21063,
    "Business": 12043,
    "Design & Composition": 3915,
    "Uncategorized": 1448,
    "Reference & Learning": 1123,
    "Social Networking": 715,
    "Utilities": 472,
    "Shopping": 382,
    "Entertainment": 87,
    "News & Opinion": 84,
    "Software Development": 32
  },
  "2020-10-20": {
    "Communication & Scheduling": 35776,
    "Business": 7448,
    "Design & Composition": 2073,
    "Reference & Learning": 1595,
    "Utilities": 745,
    "Uncategorized": 729,
    "Social Networking": 653,
    "News & Opinion": 527,
    "Entertainment": 190,
    "Shopping": 189
  },
  "2020-10-21": {
    "Communication & Scheduling": 19949,
    "Business": 9535,
    "Reference & Learning": 3154,
    "Design & Composition": 2756,
    "Uncategorized": 1914,
    "News & Opinion": 1347,
    "Social Networking": 1222,
    "Utilities": 568,
    "Software Development": 190,
    "Shopping": 76,
    "Entertainment": 51
  },
  "2020-10-22": {},
  "2020-10-23": {
    "Uncategorized": 6269,
    "Business": 3957,
    "Design & Composition": 3118,
    "Communication & Scheduling": 2985,
    "Reference & Learning": 2587,
    "News & Opinion": 1214,
    "Social Networking": 1179,
    "Utilities": 1125,
    "Entertainment": 230,
    "Shopping": 104
  },
  "2020-10-24": {
    "Design & Composition": 4593,
    "Uncategorized": 4229,
    "Business": 3672,
    "Communication & Scheduling": 1996,
    "Reference & Learning": 1265,
    "Utilities": 648,
    "News & Opinion": 583,
    "Social Networking": 228,
    "Entertainment": 182,
    "Shopping": 118
  }
}