[
  {
    "Rank": 1,
    "Time Spent (seconds)": 14931,
    "Number of People": 1,
    "Category": "Utilities"
  },
  {
    "Rank": 2,
    "Time Spent (seconds)": 11680,
    "Number of People": 1,
    "Category": "Communication & Scheduling"
  },
  {
    "Rank": 3,
    "Time Spent (seconds)": 353,
    "Number of People": 1,
    "Category": "Reference & Learning"
  },
  {
    "Rank": 4,
    "Time Spent (seconds)": 274,
    "Number of People": 1,
    "Category": "Business"
  },
  {
    "Rank": 5,
    "Time Spent (seconds)": 126,
    "Number of People": 1,
    "Category": "Design & Composition"
  },
  {
    "Rank": 6,
    "Time Spent (seconds)": 15,
    "Number of People": 1,
    "Category": "Uncategorized"
  }
]