{
  "1": {
    "Meetings": 41668,
    "Browsers": 360854,
    "Communications": 53122,
    "Project Management": 4231,
    "Writing": 41276,
    "Email": 51463,
    "Intelligence": 2128,
    "General Utilities": 5893,
    "General Reference & Learning": 5849,
    "Uncategorized": 5129,
    "Instant Message": 46679,
    "General Business": 347,
    "Engineering & Drafting": 787,
    "General Entertainment": 557,
    "General Design & Composition": 569,
    "Presentation": 6,
    "Calendars": 8592,
    "Video Editing": 3266,
    "General Shopping": 55
  },
  "2": {
    "Browsers": 281341,
    "Meetings": 41380,
    "Instant Message": 30208,
    "Communications": 31306,
    "Email": 32811,
    "Writing": 21990,
    "Calendars": 15213,
    "General Entertainment": 14218,
    "General Utilities": 3296,
    "General Reference & Learning": 1527,
    "Intelligence": 1274,
    "Engineering & Drafting": 319,
    "Uncategorized": 3702,
    "General Business": 678,
    "Legal & Gov't": 36,
    "Systems Operations": 3,
    "General Design & Composition": 2805,
    "Search": 6,
    "Voice Chat": 8,
    "General Shopping": 71
  },
  "3": {},
  "4": {},
  "5": {},
  "6": {},
  "7": {},
  "8": {},
  "9": {},
  "10": {},
  "11": {},
  "12": {}
}