{
  "1": {
    "Meetings": 37177,
    "Browsers": 261309,
    "Communications": 34336,
    "Project Management": 4231,
    "Writing": 23514,
    "Email": 33563,
    "Intelligence": 1017,
    "General Utilities": 4414,
    "General Reference & Learning": 4493,
    "Uncategorized": 3424,
    "Instant Message": 34228,
    "General Business": 80,
    "Engineering & Drafting": 737,
    "General Entertainment": 519,
    "General Design & Composition": 155,
    "Presentation": 6,
    "Calendars": 1821,
    "Video Editing": 2404,
    "General Shopping": 55
  },
  "2": {},
  "3": {},
  "4": {},
  "5": {},
  "6": {},
  "7": {},
  "8": {},
  "9": {},
  "10": {},
  "11": {},
  "12": {}
}