{
  "1": {
    "Meetings": 16915,
    "Browsers": 136162,
    "Communications": 16272,
    "Project Management": 3389,
    "Writing": 14483,
    "Email": 17136,
    "Intelligence": 675,
    "General Utilities": 2430,
    "General Reference & Learning": 4227,
    "Uncategorized": 547,
    "Instant Message": 17466,
    "General Business": 80,
    "Engineering & Drafting": 229,
    "General Entertainment": 72,
    "General Design & Composition": 3
  },
  "2": {},
  "3": {},
  "4": {},
  "5": {},
  "6": {},
  "7": {},
  "8": {},
  "9": {},
  "10": {},
  "11": {},
  "12": {}
}