{
  "2022-10-16": {
    "Uncategorized": 605,
    "Communications": 375,
    "Video": 357,
    "General Social Networking": 145,
    "Meetings": 112,
    "Search": 108,
    "Project Management": 105,
    "General Reference & Learning": 63,
    "Calendars": 54,
    "General Utilities": 46,
    "Intelligence": 43,
    "Browsers": 29,
    "Sales": 21,
    "General Entertainment": 7,
    "General Communication & Scheduling": 4
  },
  "2022-10-17": {},
  "2022-10-18": {},
  "2022-10-19": {},
  "2022-10-20": {},
  "2022-10-21": {},
  "2022-10-22": {}
}