{
  "2022-07-3": {
    "Uncategorized": 8893,
    "Business": 8031,
    "Reference & Learning": 5374,
    "Shopping": 2187,
    "Communication & Scheduling": 1556,
    "Social Networking": 863,
    "Utilities": 386,
    "Entertainment": 195,
    "News & Opinion": 87,
    "Software Development": 4,
    "Other Work": 4
  },
  "2022-07-4": {
    "Business": 11203,
    "Communication & Scheduling": 10875,
    "Other Work": 5710,
    "Reference & Learning": 4300,
    "Entertainment": 2456,
    "Uncategorized": 1377,
    "Design & Composition": 876,
    "Social Networking": 709,
    "Shopping": 650,
    "News & Opinion": 505,
    "Utilities": 270,
    "Software Development": 25
  },
  "2022-07-5": {
    "Business": 14995,
    "Communication & Scheduling": 10259,
    "Other Work": 5038,
    "Reference & Learning": 3141,
    "Uncategorized": 1972,
    "Social Networking": 367,
    "Design & Composition": 276,
    "Entertainment": 258,
    "Utilities": 243,
    "News & Opinion": 34,
    "Shopping": 7,
    "Software Development": 1
  },
  "2022-07-6": {
    "Business": 15807,
    "Communication & Scheduling": 8553,
    "Other Work": 3514,
    "Reference & Learning": 3356,
    "Entertainment": 2168,
    "Social Networking": 1770,
    "News & Opinion": 1178,
    "Uncategorized": 1131,
    "Shopping": 388,
    "Design & Composition": 252,
    "Utilities": 238
  },
  "2022-07-7": {
    "Communication & Scheduling": 11832,
    "Other Work": 4447,
    "Business": 2746,
    "Reference & Learning": 1654,
    "Social Networking": 1333,
    "Uncategorized": 838,
    "Entertainment": 581,
    "News & Opinion": 326,
    "Design & Composition": 316,
    "Utilities": 268,
    "Software Development": 6
  },
  "2022-07-8": {
    "Entertainment": 188,
    "Business": 52,
    "Reference & Learning": 8,
    "Social Networking": 4,
    "Utilities": 2,
    "Other Work": 1
  },
  "2022-07-9": {
    "Entertainment": 3541,
    "News & Opinion": 3226,
    "Communication & Scheduling": 1204,
    "Uncategorized": 176,
    "Business": 55,
    "Utilities": 15,
    "Social Networking": 13,
    "Reference & Learning": 9,
    "Other Work": 3
  }
}