{
  "2021-11-14": {
    "score": 84,
    "score_activity_balance": 95,
    "score_hrv_balance": 68,
    "score_previous_day": 100,
    "score_previous_night": 88,
    "score_recovery_index": 58,
    "score_resting_hr": 99,
    "score_sleep_balance": 80,
    "score_temperature": 100
  },
  "2021-11-15": {
    "score": 83,
    "score_activity_balance": 97,
    "score_hrv_balance": 77,
    "score_previous_day": 89,
    "score_previous_night": 75,
    "score_recovery_index": 80,
    "score_resting_hr": 90,
    "score_sleep_balance": 80,
    "score_temperature": 88
  },
  "2021-11-16": {
    "score": 81,
    "score_activity_balance": 99,
    "score_hrv_balance": 74,
    "score_previous_day": 88,
    "score_previous_night": 80,
    "score_recovery_index": 63,
    "score_resting_hr": 90,
    "score_sleep_balance": 77,
    "score_temperature": 100
  },
  "2021-11-17": {
    "score": 64,
    "score_activity_balance": 85,
    "score_hrv_balance": 66,
    "score_previous_day": 64,
    "score_previous_night": 70,
    "score_recovery_index": 38,
    "score_resting_hr": 36,
    "score_sleep_balance": 77,
    "score_temperature": 100
  },
  "2021-11-18": {},
  "2021-11-19": {
    "score": 79,
    "score_activity_balance": 87,
    "score_hrv_balance": 65,
    "score_previous_day": 89,
    "score_previous_night": 75,
    "score_recovery_index": 70,
    "score_resting_hr": 91,
    "score_sleep_balance": 77,
    "score_temperature": 100
  },
  "2021-11-20": {}
}