[
  {
    "summary_date": "2021-08-06",
    "period_id": 0,
    "is_longest": 1,
    "timezone": 120,
    "bedtime_end": "2021-08-07T07:17:00+02:00",
    "bedtime_start": "2021-08-07T00:01:00+02:00",
    "breath_average": 13,
    "duration": 26160,
    "total": 25140,
    "awake": 1020,
    "rem": 3960,
    "deep": 9750,
    "light": 11430,
    "midpoint_time": 13050,
    "efficiency": 96,
    "restless": 26,
    "onset_latency": 360,
    "hr_5min": [
      0,
      55,
      54,
      55,
      53,
      52,
      53,
      52,
      52,
      52,
      52,
      53,
      55,
      54,
      51,
      52,
      51,
      51,
      51,
      50,
      52,
      50,
      51,
      51,
      49,
      46,
      47,
      51,
      47,
      49,
      51,
      50,
      54,
      55,
      53,
      52,
      50,
      50,
      49,
      50,
      50,
      0,
      0,
      48,
      45,
      46,
      46,
      48,
      47,
      48,
      48,
      48,
      48,
      48,
      47,
      46,
      46,
      47,
      46,
      46,
      0,
      50,
      0,
      50,
      57,
      52,
      52,
      51,
      50,
      50,
      50,
      51,
      49,
      49,
      49,
      49,
      49,
      48,
      47,
      47,
      47,
      0,
      50,
      50,
      49,
      50,
      53,
      0
    ],
    "hypnogram_5min": "4211122211112222111122112221122212111111111222211222111222223333322222222111123333333344",
    "rmssd": 100,
    "rmssd_5min": [
      0,
      98,
      92,
      103,
      94,
      91,
      97,
      94,
      97,
      97,
      112,
      112,
      127,
      119,
      93,
      89,
      82,
      76,
      90,
      86,
      107,
      96,
      95,
      110,
      111,
      69,
      152,
      142,
      125,
      135,
      153,
      163,
      142,
      137,
      137,
      110,
      113,
      105,
      118,
      107,
      139,
      0,
      0,
      91,
      68,
      65,
      76,
      104,
      96,
      96,
      83,
      69,
      60,
      58,
      62,
      76,
      65,
      64,
      86,
      63,
      0,
      93,
      0,
      105,
      81,
      108,
      114,
      99,
      104,
      104,
      109,
      96,
      84,
      84,
      84,
      81,
      80,
      82,
      72,
      104,
      105,
      0,
      110,
      101,
      105,
      121,
      90,
      0
    ],
    "score": 80,
    "score_alignment": 80,
    "score_deep": 100,
    "score_disturbances": 89,
    "score_efficiency": 100,
    "score_latency": 75,
    "score_rem": 55,
    "score_total": 73,
    "temperature_deviation": -0.1,
    "temperature_trend_deviation": -0.01,
    "bedtime_start_delta": 60,
    "bedtime_end_delta": 26220,
    "midpoint_at_delta": 13110,
    "temperature_delta": -0.1,
    "hr_lowest": 45,
    "hr_average": 50.02
  }
]