[
  {
    "Rank": 1,
    "Time Spent (seconds)": 465,
    "Number of People": 1,
    "Category": "Calendars"
  },
  {
    "Rank": 2,
    "Time Spent (seconds)": 31,
    "Number of People": 1,
    "Category": "Writing"
  },
  {
    "Rank": 3,
    "Time Spent (seconds)": 22,
    "Number of People": 1,
    "Category": "General Utilities"
  },
  {
    "Rank": 4,
    "Time Spent (seconds)": 9,
    "Number of People": 1,
    "Category": "Intelligence"
  },
  {
    "Rank": 5,
    "Time Spent (seconds)": 5,
    "Number of People": 1,
    "Category": "Browsers"
  },
  {
    "Rank": 6,
    "Time Spent (seconds)": 4,
    "Number of People": 1,
    "Category": "General Design & Composition"
  }
]