{
  "2020": {
    "Entertainment": 416166,
    "Reference & Learning": 468289,
    "Uncategorized": 676096,
    "Utilities": 204166,
    "News & Opinion": 257975,
    "Social Networking": 192632,
    "Business": 2955619,
    "Communication & Scheduling": 2652603,
    "Design & Composition": 626439,
    "Shopping": 169239,
    "Software Development": 47556
  },
  "2021": {
    "Communication & Scheduling": 3808237,
    "Business": 3345527,
    "Utilities": 194317,
    "Uncategorized": 644702,
    "Reference & Learning": 392754,
    "Social Networking": 380993,
    "Design & Composition": 309779,
    "Shopping": 67005,
    "Entertainment": 463834,
    "News & Opinion": 244183,
    "Software Development": 29057
  }
}