{
  "2020": {
    "Entertainment": 416166,
    "Reference & Learning": 468289,
    "Uncategorized": 676096,
    "Utilities": 204166,
    "News & Opinion": 257975,
    "Social Networking": 192632,
    "Business": 2955619,
    "Communication & Scheduling": 2652603,
    "Design & Composition": 626439,
    "Shopping": 169239,
    "Software Development": 47556
  },
  "2021": {
    "Communication & Scheduling": 5956,
    "Business": 24879,
    "Utilities": 1488,
    "Uncategorized": 3623,
    "Reference & Learning": 4201,
    "Social Networking": 2598,
    "Design & Composition": 12896,
    "Shopping": 885,
    "Entertainment": 898,
    "News & Opinion": 1273,
    "Software Development": 117
  }
}